setup.py
dsnd_prob_ut/Binomialdistribution.py
dsnd_prob_ut/Gaussiandistribution.py
dsnd_prob_ut/Generaldistribution.py
dsnd_prob_ut/__init__.py
dsnd_prob_ut.egg-info/PKG-INFO
dsnd_prob_ut.egg-info/SOURCES.txt
dsnd_prob_ut.egg-info/dependency_links.txt
dsnd_prob_ut.egg-info/not-zip-safe
dsnd_prob_ut.egg-info/top_level.txt